clip/__init__.py
clip/bpe_simple_vocab_16e6.txt.gz
clip/clip.py
clip/model.py
clip/simple_tokenizer.py
rf_clip-1.1.dist-info/LICENSE
rf_clip-1.1.dist-info/METADATA
rf_clip-1.1.dist-info/WHEEL
rf_clip-1.1.dist-info/top_level.txt
rf_clip-1.1.dist-info/RECORD
