Metadata-Version: 2.1
Name: rf-clip
Version: 1.1
Author: OpenAI
License-File: LICENSE
Requires-Dist: ftfy
Requires-Dist: packaging
Requires-Dist: regex
Requires-Dist: tqdm
Requires-Dist: torch
Requires-Dist: torchvision
Provides-Extra: dev
Requires-Dist: pytest ; extra == 'dev'
